[ 
 
{ 
"title"    : "Akerstraat 1", 
"desc"     : "Akerstraat 1", 
"category" : "blog, leven, akertraat posse", 
"url"      : "/2026-05-13-Akerstraat-1/", 
"date"     : "May 13, 2026" 
}, 
 
{ 
"title"    : "Proletenplofjes", 
"desc"     : "Proletenplofjes", 
"category" : "blog, leven", 
"url"      : "/2026-05-10-Proletenplofjes/", 
"date"     : "May 10, 2026" 
}, 
 
{ 
"title"    : "Verward persoon", 
"desc"     : "Verward persoon", 
"category" : "blog, leven", 
"url"      : "/2026-05-06-Verward-persoon/", 
"date"     : "May  6, 2026" 
}, 
 
{ 
"title"    : "Lullige tragiek", 
"desc"     : "Lullige tragiek", 
"category" : "blog, leven, memoire, vader", 
"url"      : "/2026-05-03-lullige-tragiek/", 
"date"     : "May  3, 2026" 
}, 
 
 
{ 
"title"    : "Nyarna", 
"desc"     : "Nyarna", 
"category" : "page", 
"url"      : "/", 
"date"     : "January 1, 1970" 
}, 
 
{ 
"title"    : "Wat is dit?", 
"desc"     : "Wat is dit?", 
"category" : "page", 
"url"      : "/page_de_auteur/", 
"date"     : "January 1, 1970" 
}, 
 
{ 
"title"    : "Tag Index", 
"desc"     : "Tag Index", 
"category" : "page", 
"url"      : "/tags/", 
"date"     : "January 1, 1970" 
} 
 
]
